{
    "sources": [
        {
            "enabled": true,
            "name": "Noctalia Plugins",
            "url": "https://github.com/noctalia-dev/noctalia-plugins"
        }
    ],
    "states": {
        "fancy-audiovisualizer": {
            "enabled": true,
            "sourceUrl": "https://github.com/noctalia-dev/noctalia-plugins"
        },
        "hot-corners": {
            "enabled": true,
            "sourceUrl": "https://github.com/noctalia-dev/noctalia-plugins"
        },
        "kagi-quick-search": {
            "enabled": false,
            "sourceUrl": "https://github.com/noctalia-dev/noctalia-plugins"
        },
        "keybind-cheatsheet": {
            "enabled": true,
            "sourceUrl": "https://github.com/noctalia-dev/noctalia-plugins"
        },
        "niri-overview-launcher": {
            "enabled": true,
            "sourceUrl": "https://github.com/noctalia-dev/noctalia-plugins"
        },
        "polkit-agent": {
            "enabled": true,
            "sourceUrl": "https://github.com/noctalia-dev/noctalia-plugins"
        },
        "privacy-indicator": {
            "enabled": true,
            "sourceUrl": "https://github.com/noctalia-dev/noctalia-plugins"
        },
        "screen-recorder": {
            "enabled": true,
            "sourceUrl": "https://github.com/noctalia-dev/noctalia-plugins"
        },
        "unicode-picker": {
            "enabled": true,
            "sourceUrl": "https://github.com/noctalia-dev/noctalia-plugins"
        }
    },
    "version": 2
}
